payout/__init__.py
payout/add_payout_rate.py
payout/add_payout_token.py
payout/create_payout_account.py
payout/find_payout_account.py
payout/payout.py
payout/start_payouts.py
payout/stop_payouts.py
payout/update_payout_account.py
payout-1.1.2.dist-info/LICENCE
payout-1.1.2.dist-info/METADATA
payout-1.1.2.dist-info/WHEEL
payout-1.1.2.dist-info/top_level.txt
payout-1.1.2.dist-info/RECORD
