Metadata-Version: 2.1
Name: payout
Version: 1.1.2
Summary: Python API for integrating with the Red Shepherd Payouts
Home-page: https://bitbucket.org/redshepherdinc/python-payout-api.git
Author: Red Shepherd Inc.
Author-email: support@redshepherd.com
License: UNKNOWN
Platform: UNKNOWN
Classifier: Development Status :: 5 - Production/Stable
Classifier: Intended Audience :: Developers
Classifier: Topic :: Software Development :: Build Tools
Classifier: License :: OSI Approved :: MIT License
Classifier: Programming Language :: Python :: 3
Classifier: Programming Language :: Python :: 3.4
Classifier: Programming Language :: Python :: 3.5
Classifier: Programming Language :: Python :: 3.6
Requires-Python: >=3.5
